segment_multiwell_plate/__init__.py
segment_multiwell_plate/__version__.py
segment_multiwell_plate/segment_multiwell_plate.py
segment_multiwell_plate-0.5.3.dist-info/LICENSE
segment_multiwell_plate-0.5.3.dist-info/METADATA
segment_multiwell_plate-0.5.3.dist-info/WHEEL
segment_multiwell_plate-0.5.3.dist-info/top_level.txt
segment_multiwell_plate-0.5.3.dist-info/RECORD
