Metadata-Version: 2.1
Name: segment-multiwell-plate
Version: 0.5.3
Summary: segment_multiwell_plate: Automatically divide multi-well plate into separate images of each well
Home-page: https://github.com/murraycutforth/segment-multiwell-plate
Author: Murray Cutforth
Author-email: murray.cutforth@gmail.com
License: GPL 2.0
Keywords: multiwell plate segmentation segment screen image analysis bioinformatics
Classifier: Development Status :: 4 - Beta
Classifier: Intended Audience :: Developers
Classifier: Programming Language :: Python :: 3.11
Requires-Python: >=3.11
License-File: LICENSE
Requires-Dist: numpy
Requires-Dist: scipy
Requires-Dist: scikit-image
